nngt/nngt.conf.default
nngt/__init__.py
nngt/io/loading_helpers.py
nngt/io/graph_loading.py
nngt/io/io_helpers.py
nngt/io/graph_saving.py
nngt/io/__init__.py
nngt/io/saving_helpers.py
nngt/database/db_generation.py
nngt/database/csv_utils.py
nngt/database/db_main.py
nngt/database/pickle_field.py
nngt/database/__init__.py
nngt/plot/animations.py
nngt/plot/hive_helpers.py
nngt/plot/plt_properties.py
nngt/plot/custom_plt.py
nngt/plot/__init__.py
nngt/plot/plt_networks.py
nngt/plot/chord_diag/chord_diagram.py
nngt/plot/chord_diag/README.md
nngt/plot/chord_diag/gradient.py
nngt/plot/chord_diag/utilities.py
nngt/plot/chord_diag/example.py
nngt/plot/chord_diag/__init__.py
nngt/generation/func_connect.cpp
nngt/generation/cconnect.pxd
nngt/generation/connectors.py
nngt/generation/mpi_connect.py
nngt/generation/graph_connectivity.py
nngt/generation/cconnect.cpython-312-x86_64-linux-gnu.so
nngt/generation/cconnect.pyx
nngt/generation/func_connect.h
nngt/generation/rewiring.py
nngt/generation/connect_algorithms.py
nngt/generation/cconnect.pyxbld
nngt/generation/__init__.py
nngt/simulation/nest_activity.py
nngt/simulation/nest_utils.py
nngt/simulation/nest_plot.py
nngt/simulation/nest_graph.py
nngt/simulation/__init__.py
nngt/lib/db_tools.py
nngt/lib/logger.py
nngt/lib/converters.py
nngt/lib/connect_tools.py
nngt/lib/_frozendict.py
nngt/lib/graph_backends.py
nngt/lib/sorting.py
nngt/lib/constants.py
nngt/lib/graph_helpers.py
nngt/lib/rng_tools.py
nngt/lib/decorator.py
nngt/lib/errors.py
nngt/lib/nngt_config.py
nngt/lib/__init__.py
nngt/lib/test_functions.py
nngt/geometry/shape.py
nngt/geometry/svgtools.py
nngt/geometry/README.md
nngt/geometry/tools.py
nngt/geometry/plot.py
nngt/geometry/backup_shape.py
nngt/geometry/geom_utils.py
nngt/geometry/dxftools.py
nngt/geometry/units.py
nngt/geometry/pync_log.py
nngt/geometry/shape_io.py
nngt/geometry/__init__.py
nngt/geometry/triangulate.py
NNGT-2.8.0.dist-info/Python-2.0.txt
NNGT-2.8.0.dist-info/RECORD
NNGT-2.8.0.dist-info/BSD-2-Clause.txt
NNGT-2.8.0.dist-info/GPL-3.0-or-later.txt
NNGT-2.8.0.dist-info/METADATA
NNGT-2.8.0.dist-info/top_level.txt
NNGT-2.8.0.dist-info/CC0-1.0.txt
NNGT-2.8.0.dist-info/WHEEL
NNGT-2.8.0.dist-info/CC-BY-SA-4.0.txt
