Metadata-Version: 2.1
Name: NNGT
Version: 2.8.0
Summary: Python package to generate and study graphs and detailed spatial or biological networks.
Author-email: Tanguy Fardet <tanguyfardet@protonmail.com>
License: GNU GENERAL PUBLIC LICENSE
Project-URL: repository, https://git.sr.ht/~tfardet/NNGT
Project-URL: documentation, https://nngt.readthedocs.io/en/stable
Keywords: network,graph,structure,igraph,graph-tool,networkx,simulation,neuron,NEST,DeNSE,topology,growth,geospatial
Classifier: Development Status :: 5 - Production/Stable
Classifier: Intended Audience :: Science/Research
Classifier: License :: OSI Approved :: GNU General Public License v3 or later (GPLv3+)
Classifier: Natural Language :: English
Classifier: Programming Language :: Python :: 3
Classifier: Programming Language :: Cython
Classifier: Programming Language :: C++
Classifier: Operating System :: OS Independent
Classifier: Topic :: Software Development :: Libraries :: Python Modules
Classifier: Topic :: Scientific/Engineering :: Information Analysis
Classifier: Topic :: Scientific/Engineering :: Mathematics
Classifier: Topic :: Scientific/Engineering :: Bio-Informatics
Classifier: Topic :: Scientific/Engineering :: Physics
Requires-Python: >=3.7
License-File: LICENSES/BSD-2-Clause.txt
License-File: LICENSES/CC-BY-SA-4.0.txt
License-File: LICENSES/CC0-1.0.txt
License-File: LICENSES/GPL-3.0-or-later.txt
License-File: LICENSES/Python-2.0.txt
Requires-Dist: cython
Requires-Dist: platformdirs
Requires-Dist: numpy >=1.17
Requires-Dist: scipy >=0.11
Provides-Extra: full
Requires-Dist: networkx >=2.4 ; extra == 'full'
Requires-Dist: shapely >=2 ; extra == 'full'
Requires-Dist: dxfgrabber ; extra == 'full'
Requires-Dist: svg.path >=4 ; extra == 'full'
Requires-Dist: matplotlib >=3.6.0 ; extra == 'full'
Requires-Dist: geopandas ; extra == 'full'
Requires-Dist: descartes ; extra == 'full'
Requires-Dist: cartopy >=0.20 ; extra == 'full'
Requires-Dist: lxml ; extra == 'full'
Provides-Extra: geometry
Requires-Dist: matplotlib >3.6.0 ; extra == 'geometry'
Requires-Dist: shapely >=2 ; extra == 'geometry'
Requires-Dist: dxfgrabber ; extra == 'geometry'
Requires-Dist: svg.path ; extra == 'geometry'
Provides-Extra: geospatial
Requires-Dist: matplotlib >3.6.0 ; extra == 'geospatial'
Requires-Dist: geopandas ; extra == 'geospatial'
Requires-Dist: descartes ; extra == 'geospatial'
Requires-Dist: cartopy >=0.20 ; extra == 'geospatial'
Provides-Extra: ig
Requires-Dist: igraph >=0.10 ; extra == 'ig'
Provides-Extra: matplotlib
Requires-Dist: matplotlib >=3.6.0 ; extra == 'matplotlib'
Provides-Extra: nx
Requires-Dist: networkx >=2.4 ; extra == 'nx'
